BVCscrap/Notation.py
BVCscrap/__init__.py
BVCscrap/load.py
BVCscrap/tech.py
BVCscrap/utils.py
BVCscrap-0.2.0.dist-info/LICENSE.txt
BVCscrap-0.2.0.dist-info/METADATA
BVCscrap-0.2.0.dist-info/WHEEL
BVCscrap-0.2.0.dist-info/top_level.txt
BVCscrap-0.2.0.dist-info/RECORD
