Metadata-Version: 2.1
Name: BVCscrap
Version: 0.2.0
Summary: Python library to scrape financial data from Casablanca Stock Exchange(Bourse des Valeurs de Casablanca)
Home-page: https://github.com/AmineAndam04/BVCscrap
Author: ANDAM Amine
Author-email: andamamine83@gmail.com
Keywords: Web scrapping,financial data,Bourse des Valeurs de Casablanca
Classifier: Programming Language :: Python :: 3
Classifier: License :: OSI Approved :: MIT License
Classifier: Operating System :: OS Independent
Requires-Python: >=3.6
License-File: LICENSE.txt
